arma3query.py
arma3query-1.3.dist-info/licenses/LICENSE
arma3query-1.3.dist-info/METADATA
arma3query-1.3.dist-info/WHEEL
arma3query-1.3.dist-info/top_level.txt
arma3query-1.3.dist-info/RECORD
