Metadata-Version: 2.4
Name: arma3query
Version: 1.3
Summary: Small module to decode the Arma 3 rules binary response.
Home-page: https://github.com/jishnukarri/arma3-a2s
Author: Jishnu Karri
Author-email: me@jishnukarri.me
License: MIT
Classifier: License :: OSI Approved :: MIT License
Classifier: Programming Language :: Python :: 3
Classifier: Operating System :: OS Independent
Classifier: Topic :: Games/Entertainment
Requires-Python: >=3.10
License-File: LICENSE
Requires-Dist: python-a2s
Dynamic: author
Dynamic: author-email
Dynamic: classifier
Dynamic: description
Dynamic: description-content-type
Dynamic: home-page
Dynamic: license
Dynamic: license-file
Dynamic: requires-dist
Dynamic: requires-python
Dynamic: summary
